odoo8_addon_product_by_supplier-8.0.1.0.0.99.dev32-py2.7-nspkg.pth
odoo8_addon_product_by_supplier-8.0.1.0.0.99.dev32.dist-info/DESCRIPTION.rst
odoo8_addon_product_by_supplier-8.0.1.0.0.99.dev32.dist-info/METADATA
odoo8_addon_product_by_supplier-8.0.1.0.0.99.dev32.dist-info/RECORD
odoo8_addon_product_by_supplier-8.0.1.0.0.99.dev32.dist-info/WHEEL
odoo8_addon_product_by_supplier-8.0.1.0.0.99.dev32.dist-info/metadata.json
odoo8_addon_product_by_supplier-8.0.1.0.0.99.dev32.dist-info/namespace_packages.txt
odoo8_addon_product_by_supplier-8.0.1.0.0.99.dev32.dist-info/top_level.txt
odoo_addons/product_by_supplier/README.rst
odoo_addons/product_by_supplier/__init__.py
odoo_addons/product_by_supplier/__openerp__.py
odoo_addons/product_by_supplier/i18n/bg.po
odoo_addons/product_by_supplier/i18n/ca.po
odoo_addons/product_by_supplier/i18n/de.po
odoo_addons/product_by_supplier/i18n/el_GR.po
odoo_addons/product_by_supplier/i18n/es.po
odoo_addons/product_by_supplier/i18n/es_ES.po
odoo_addons/product_by_supplier/i18n/eu.po
odoo_addons/product_by_supplier/i18n/fi.po
odoo_addons/product_by_supplier/i18n/fr.po
odoo_addons/product_by_supplier/i18n/fr_CH.po
odoo_addons/product_by_supplier/i18n/fr_FR.po
odoo_addons/product_by_supplier/i18n/gl.po
odoo_addons/product_by_supplier/i18n/hr.po
odoo_addons/product_by_supplier/i18n/hr_HR.po
odoo_addons/product_by_supplier/i18n/it.po
odoo_addons/product_by_supplier/i18n/nl.po
odoo_addons/product_by_supplier/i18n/nl_NL.po
odoo_addons/product_by_supplier/i18n/product_by_supplier.pot
odoo_addons/product_by_supplier/i18n/pt.po
odoo_addons/product_by_supplier/i18n/pt_BR.po
odoo_addons/product_by_supplier/i18n/pt_PT.po
odoo_addons/product_by_supplier/i18n/ro.po
odoo_addons/product_by_supplier/i18n/ru.po
odoo_addons/product_by_supplier/i18n/sk.po
odoo_addons/product_by_supplier/i18n/sl.po
odoo_addons/product_by_supplier/i18n/tr.po
odoo_addons/product_by_supplier/i18n/tr_TR.po
odoo_addons/product_by_supplier/i18n/vi_VN.po
odoo_addons/product_by_supplier/i18n/zh_CN.po
odoo_addons/product_by_supplier/models/__init__.py
odoo_addons/product_by_supplier/models/product_supplierinfo.py
odoo_addons/product_by_supplier/static/description/icon.png
odoo_addons/product_by_supplier/static/description/index.html
odoo_addons/product_by_supplier/static/images/product_supplier_info.png
odoo_addons/product_by_supplier/views/product_supplierinfo_view.xml
